jupytercheckpoints/__init__.py
jupytercheckpoints/checkpoints.py
jupytercheckpoints/contents_manager.py
jupytercheckpoints/extension.py
jupytercheckpoints/extension/install.json
jupytercheckpoints/extension/jupyter_server_config.json
jupytercheckpoints/extension/jupyter_server_config.d/jupytercheckpoints.json
jupyter_checkpoints-0.3.0.data/data/etc/jupyter/jupyter_server_config.d/jupytercheckpoints.json
jupyter_checkpoints-0.3.0.dist-info/METADATA
jupyter_checkpoints-0.3.0.dist-info/WHEEL
jupyter_checkpoints-0.3.0.dist-info/RECORD
