Metadata-Version: 2.4
Name: jupyter-checkpoints
Version: 0.3.0
Summary: A JupyterLab extension for managing multiple checkpoints
License: MIT
Classifier: Framework :: Jupyter
Classifier: Framework :: Jupyter :: JupyterLab
Classifier: Framework :: Jupyter :: JupyterLab :: 4
Classifier: Programming Language :: Python
Classifier: Programming Language :: Python :: 3.12
Requires-Python: >=3.12
Requires-Dist: jupyter-server>=2.16.0
